{"_type":"export","__export_format":4,"__export_date":"2022-03-21T01:06:37.155Z","__export_source":"insomnia.desktop.app:v2022.2.0","resources":[{"_id":"req_095a8d3420b64c80a81bd69c17d83d0d","parentId":"fld_c923a32119cf432181125b80a67738ef","modified":1647727522787,"created":1647727460099,"url":"http://localhost:3333/deletar-variedade/3","name":"deletarVariedade","description":"","method":"DELETE","body":{},"parameters":[],"headers":[],"authentication":{},"metaSortKey":-1647727460099,"isPrivate":false,"settingStoreCookies":true,"settingSendCookies":true,"settingDisableRenderRequestBody":false,"settingEncodeUrl":true,"settingRebuildPath":true,"settingFollowRedirects":"global","_type":"request"},{"_id":"fld_c923a32119cf432181125b80a67738ef","parentId":"wrk_9d2642ba0e644f468825d682d3f05ecf","modified":1647727172944,"created":1647727172944,"name":"Variedade","description":"","environment":{},"environmentPropertyOrder":null,"metaSortKey":-1647727172944,"_type":"request_group"},{"_id":"wrk_9d2642ba0e644f468825d682d3f05ecf","parentId":null,"modified":1646182968065,"created":1646182968065,"name":"api-cafe","description":"","scope":"design","_type":"workspace"},{"_id":"req_270c76fbdb9f42feabbb8188cf67c089","parentId":"fld_c923a32119cf432181125b80a67738ef","modified":1647822767488,"created":1647727379587,"url":"http://localhost:3333/atulizar-variedade/1","name":"atualizaVariedade","description":"","method":"PUT","body":{"mimeType":"application/json","text":"{\n\t\"nome\":\"Bourbon amarelo\",\n\t\"descricao\":\"Nenhuma descrição\"\n}"},"parameters":[],"headers":[{"name":"Content-Type","value":"application/json","id":"pair_1900406a442a454cafb0df5868246910"}],"authentication":{},"metaSortKey":-1647727379587,"isPrivate":false,"settingStoreCookies":true,"settingSendCookies":true,"settingDisableRenderRequestBody":false,"settingEncodeUrl":true,"settingRebuildPath":true,"settingFollowRedirects":"global","_type":"request"},{"_id":"req_aa0f63dcada8458dbddb561ae1303456","parentId":"fld_c923a32119cf432181125b80a67738ef","modified":1647727353805,"created":1647727325458,"url":"http://localhost:3333/buscar-um-variedade/2","name":"buscarUmaVariedade","description":"","method":"GET","body":{},"parameters":[],"headers":[],"authentication":{},"metaSortKey":-1647727325458,"isPrivate":false,"settingStoreCookies":true,"settingSendCookies":true,"settingDisableRenderRequestBody":false,"settingEncodeUrl":true,"settingRebuildPath":true,"settingFollowRedirects":"global","_type":"request"},{"_id":"req_30d77769db8442b69dba947f8afb609a","parentId":"fld_c923a32119cf432181125b80a67738ef","modified":1647727302386,"created":1647727283746,"url":"http://localhost:3333/listar-variedade","name":"listarVariedade","description":"","method":"GET","body":{},"parameters":[],"headers":[],"authentication":{},"metaSortKey":-1647727283746,"isPrivate":false,"settingStoreCookies":true,"settingSendCookies":true,"settingDisableRenderRequestBody":false,"settingEncodeUrl":true,"settingRebuildPath":true,"settingFollowRedirects":"global","_type":"request"},{"_id":"req_3448b9039f1c483fb02128fe3925b806","parentId":"fld_c923a32119cf432181125b80a67738ef","modified":1647823167733,"created":1647727197612,"url":"http://localhost:3333/cadastrar-variedade","name":"cadastraVariedade","description":"","method":"POST","body":{"mimeType":"application/json","text":"{\n\t\"nome\":\"Bourbon amarelo\",\n\t\"descricao\":\"Nenhuma descrição\"\n}"},"parameters":[],"headers":[{"name":"Content-Type","value":"application/json","id":"pair_0d2170b38ba34cc2a382415414801626"}],"authentication":{},"metaSortKey":-1647727197612,"isPrivate":false,"settingStoreCookies":true,"settingSendCookies":true,"settingDisableRenderRequestBody":false,"settingEncodeUrl":true,"settingRebuildPath":true,"settingFollowRedirects":"global","_type":"request"},{"_id":"req_30a88635b57642e79ef3a9d6ef160536","parentId":"fld_a74793c8db084613a31d01b2208ee021","modified":1647727047643,"created":1647727033115,"url":"http://localhost:3333/deletar-torra/1","name":"deletarTorra","description":"","method":"DELETE","body":{},"parameters":[],"headers":[],"authentication":{},"metaSortKey":-1647727033115,"isPrivate":false,"settingStoreCookies":true,"settingSendCookies":true,"settingDisableRenderRequestBody":false,"settingEncodeUrl":true,"settingRebuildPath":true,"settingFollowRedirects":"global","_type":"request"},{"_id":"fld_a74793c8db084613a31d01b2208ee021","parentId":"wrk_9d2642ba0e644f468825d682d3f05ecf","modified":1647726712938,"created":1647726712938,"name":"Torra","description":"","environment":{},"environmentPropertyOrder":null,"metaSortKey":-1647726712938,"_type":"request_group"},{"_id":"req_0f764911b8804a6aa54d9114e4b9d4b8","parentId":"fld_a74793c8db084613a31d01b2208ee021","modified":1647822401402,"created":1647726959403,"url":"http://localhost:3333/atulizar-torra/1","name":"atualizarTorra","description":"","method":"PUT","body":{"mimeType":"application/json","text":"{\n\t\"nome\":\"Média\",\n\t\"descricao\":\"Nenhuma descrição\"\n}"},"parameters":[],"headers":[{"name":"Content-Type","value":"application/json","id":"pair_d904f7904b1342f4a86ae4e6bf0fb179"}],"authentication":{},"metaSortKey":-1647726959403,"isPrivate":false,"settingStoreCookies":true,"settingSendCookies":true,"settingDisableRenderRequestBody":false,"settingEncodeUrl":true,"settingRebuildPath":true,"settingFollowRedirects":"global","_type":"request"},{"_id":"req_e7477c987b20461b92195fae444d4a1a","parentId":"fld_a74793c8db084613a31d01b2208ee021","modified":1647822101652,"created":1647726889330,"url":"http://localhost:3333/buscar-um-torra/3","name":"buscarUmaTorra","description":"","method":"GET","body":{},"parameters":[],"headers":[],"authentication":{},"metaSortKey":-1647726889330,"isPrivate":false,"settingStoreCookies":true,"settingSendCookies":true,"settingDisableRenderRequestBody":false,"settingEncodeUrl":true,"settingRebuildPath":true,"settingFollowRedirects":"global","_type":"request"},{"_id":"req_a8589c7ee192415cb97a58e9c5fca752","parentId":"fld_a74793c8db084613a31d01b2208ee021","modified":1647726825453,"created":1647726801650,"url":"http://localhost:3333/listar-torra","name":"listarTorra","description":"","method":"GET","body":{},"parameters":[],"headers":[],"authentication":{},"metaSortKey":-1647726801650,"isPrivate":false,"settingStoreCookies":true,"settingSendCookies":true,"settingDisableRenderRequestBody":false,"settingEncodeUrl":true,"settingRebuildPath":true,"settingFollowRedirects":"global","_type":"request"},{"_id":"req_0e0fa75e3a1b4ed9b32c1804da1c3e9f","parentId":"fld_a74793c8db084613a31d01b2208ee021","modified":1647822516749,"created":1647726730763,"url":"http://localhost:3333/cadastrar-torra","name":"cadastraTorra","description":"","method":"POST","body":{"mimeType":"application/json","text":"{\n\t\"nome\":\"Média\",\n\t\"descricao\":\"Nenhuma descrição\"\n}"},"parameters":[],"headers":[{"name":"Content-Type","value":"application/json","id":"pair_b966b3e0b41542889af5091c4adaa853"}],"authentication":{},"metaSortKey":-1647726730763,"isPrivate":false,"settingStoreCookies":true,"settingSendCookies":true,"settingDisableRenderRequestBody":false,"settingEncodeUrl":true,"settingRebuildPath":true,"settingFollowRedirects":"global","_type":"request"},{"_id":"req_349c3c3629094dbe8a68b0972ce8d9a8","parentId":"fld_fa1f42e9dff94819b59e9546c19e5405","modified":1647726932985,"created":1647726587641,"url":"http://localhost:3333/deletar-moagem/1","name":"deletarMoagem","description":"","method":"DELETE","body":{},"parameters":[],"headers":[],"authentication":{},"metaSortKey":-1647726587641,"isPrivate":false,"settingStoreCookies":true,"settingSendCookies":true,"settingDisableRenderRequestBody":false,"settingEncodeUrl":true,"settingRebuildPath":true,"settingFollowRedirects":"global","_type":"request"},{"_id":"fld_fa1f42e9dff94819b59e9546c19e5405","parentId":"wrk_9d2642ba0e644f468825d682d3f05ecf","modified":1647726231847,"created":1647726231847,"name":"Moagem","description":"","environment":{},"environmentPropertyOrder":null,"metaSortKey":-1647726231847,"_type":"request_group"},{"_id":"req_600b31a4ba734aed8c9611482f9284ce","parentId":"fld_fa1f42e9dff94819b59e9546c19e5405","modified":1647822409924,"created":1647726539523,"url":"http://localhost:3333/atulizar-moagem/2","name":"atualizarMoagem","description":"","method":"PUT","body":{"mimeType":"application/json","text":"{\n\t\"nome\":\"Fina\"\n}"},"parameters":[],"headers":[{"name":"Content-Type","value":"application/json","id":"pair_bd7d7e40368e42cba5429078c58011d5"}],"authentication":{},"metaSortKey":-1647726539523,"isPrivate":false,"settingStoreCookies":true,"settingSendCookies":true,"settingDisableRenderRequestBody":false,"settingEncodeUrl":true,"settingRebuildPath":true,"settingFollowRedirects":"global","_type":"request"},{"_id":"req_bd70e962a9ec4e4a8b9fd0072d2f78c5","parentId":"fld_fa1f42e9dff94819b59e9546c19e5405","modified":1647726513285,"created":1647726493442,"url":"http://localhost:3333/buscar-um-moagem/2","name":"buscarUmaMoagem","description":"","method":"GET","body":{},"parameters":[],"headers":[],"authentication":{},"metaSortKey":-1647726493442,"isPrivate":false,"settingStoreCookies":true,"settingSendCookies":true,"settingDisableRenderRequestBody":false,"settingEncodeUrl":true,"settingRebuildPath":true,"settingFollowRedirects":"global","_type":"request"},{"_id":"req_9106649532554100be86985b9ec0b615","parentId":"fld_fa1f42e9dff94819b59e9546c19e5405","modified":1647726405007,"created":1647726385242,"url":"http://localhost:3333/listar-moagem","name":"listarMoagem","description":"","method":"GET","body":{},"parameters":[],"headers":[],"authentication":{},"metaSortKey":-1647725737225.5,"isPrivate":false,"settingStoreCookies":true,"settingSendCookies":true,"settingDisableRenderRequestBody":false,"settingEncodeUrl":true,"settingRebuildPath":true,"settingFollowRedirects":"global","_type":"request"},{"_id":"req_687100cd670d4874bb936a1df8f42f8a","parentId":"fld_fa1f42e9dff94819b59e9546c19e5405","modified":1647822497268,"created":1647726319785,"url":"http://localhost:3333/cadastrar-moagem","name":"cadastraMoagem","description":"","method":"POST","body":{"mimeType":"application/json","text":"{\n\t\"nome\":\"Fina\"\n}"},"parameters":[],"headers":[{"name":"Content-Type","value":"application/json","id":"pair_a1f741015f9c4ea4878fad939b41efaa"}],"authentication":{},"metaSortKey":-1647725737175.5,"isPrivate":false,"settingStoreCookies":true,"settingSendCookies":true,"settingDisableRenderRequestBody":false,"settingEncodeUrl":true,"settingRebuildPath":true,"settingFollowRedirects":"global","_type":"request"},{"_id":"req_ea3876eff42c41cab797eb05ce8a52a9","parentId":"fld_b5fc8e924e2d4a2a86bf7d5862427600","modified":1647725763354,"created":1647725730513,"url":"http://localhost:3333/listar-corpo","name":"listarCorpo","description":"","method":"GET","body":{},"parameters":[],"headers":[],"authentication":{},"metaSortKey":-1647725730513,"isPrivate":false,"settingStoreCookies":true,"settingSendCookies":true,"settingDisableRenderRequestBody":false,"settingEncodeUrl":true,"settingRebuildPath":true,"settingFollowRedirects":"global","_type":"request"},{"_id":"fld_b5fc8e924e2d4a2a86bf7d5862427600","parentId":"wrk_9d2642ba0e644f468825d682d3f05ecf","modified":1647725242504,"created":1647725242504,"name":"Corpo","description":"","environment":{},"environmentPropertyOrder":null,"metaSortKey":-1647725242504,"_type":"request_group"},{"_id":"req_52b98e42db65451b898ca4355884ef27","parentId":"fld_b5fc8e924e2d4a2a86bf7d5862427600","modified":1647725794041,"created":1647725702017,"url":"http://localhost:3333/buscar-um-corpo/1","name":"buscarUmCorpo","description":"","method":"GET","body":{},"parameters":[],"headers":[],"authentication":{},"metaSortKey":-1647725702017,"isPrivate":false,"settingStoreCookies":true,"settingSendCookies":true,"settingDisableRenderRequestBody":false,"settingEncodeUrl":true,"settingRebuildPath":true,"settingFollowRedirects":"global","_type":"request"},{"_id":"req_c8f81999e59149f09b58e3ebc902e3cf","parentId":"fld_b5fc8e924e2d4a2a86bf7d5862427600","modified":1647725814580,"created":1647725665344,"url":"http://localhost:3333/deletar-corpo/1","name":"deletarCorpo","description":"","method":"DELETE","body":{},"parameters":[],"headers":[],"authentication":{},"metaSortKey":-1647725665344,"isPrivate":false,"settingStoreCookies":true,"settingSendCookies":true,"settingDisableRenderRequestBody":false,"settingEncodeUrl":true,"settingRebuildPath":true,"settingFollowRedirects":"global","_type":"request"},{"_id":"req_57816f808f4a45af81930f9667d770c4","parentId":"fld_b5fc8e924e2d4a2a86bf7d5862427600","modified":1647822418755,"created":1647725644760,"url":"http://localhost:3333/atulizar-corpo/2","name":"atualizarCorpo","description":"","method":"PUT","body":{"mimeType":"application/json","text":"{\n\t\"nome\":\"Cremoso\"\n}"},"parameters":[],"headers":[{"name":"Content-Type","value":"application/json","id":"pair_2c6026b780c94fc998423e96fe699139"}],"authentication":{},"metaSortKey":-1647725644760,"isPrivate":false,"settingStoreCookies":true,"settingSendCookies":true,"settingDisableRenderRequestBody":false,"settingEncodeUrl":true,"settingRebuildPath":true,"settingFollowRedirects":"global","_type":"request"},{"_id":"req_9e93586c9e83493cb5279cff9f27b331","parentId":"fld_b5fc8e924e2d4a2a86bf7d5862427600","modified":1647822483585,"created":1647725270504,"url":"http://localhost:3333/cadastrar-corpo","name":"cadastraCorpo","description":"","method":"POST","body":{"mimeType":"application/json","text":"{\n\t\"nome\":\"Cremoso\"\n}"},"parameters":[],"headers":[{"name":"Content-Type","value":"application/json","id":"pair_8aa153828a10414498cce3361b4e5c8d"}],"authentication":{},"metaSortKey":-1647725270504,"isPrivate":false,"settingStoreCookies":true,"settingSendCookies":true,"settingDisableRenderRequestBody":false,"settingEncodeUrl":true,"settingRebuildPath":true,"settingFollowRedirects":"global","_type":"request"},{"_id":"req_7858796b6455477fa1707a3c369c5709","parentId":"fld_1374896991c8448c9401786505583995","modified":1647822422544,"created":1647710570090,"url":"http://localhost:3333/atulizar-acidez/2","name":"atulizarAcidez","description":"","method":"PUT","body":{"mimeType":"application/json","text":"{\n\t\"nome\":\"Média alta\",\n\t\"descricao\":\"Nenhuma descrição\"\n}"},"parameters":[],"headers":[{"name":"Content-Type","value":"application/json","id":"pair_d46ef924e7154485ada93610a013aa29"}],"authentication":{},"metaSortKey":-1647710570090,"isPrivate":false,"settingStoreCookies":true,"settingSendCookies":true,"settingDisableRenderRequestBody":false,"settingEncodeUrl":true,"settingRebuildPath":true,"settingFollowRedirects":"global","_type":"request"},{"_id":"fld_1374896991c8448c9401786505583995","parentId":"wrk_9d2642ba0e644f468825d682d3f05ecf","modified":1647706431199,"created":1647706431199,"name":"Acidez","description":"","environment":{},"environmentPropertyOrder":null,"metaSortKey":-1647706431199,"_type":"request_group"},{"_id":"req_f263a5a976bf483b8dce1fcf42648cee","parentId":"fld_1374896991c8448c9401786505583995","modified":1647709196990,"created":1647709170665,"url":"http://localhost:3333/deletar-acidez/1","name":"deletar","description":"","method":"DELETE","body":{},"parameters":[],"headers":[],"authentication":{},"metaSortKey":-1647709170665,"isPrivate":false,"settingStoreCookies":true,"settingSendCookies":true,"settingDisableRenderRequestBody":false,"settingEncodeUrl":true,"settingRebuildPath":true,"settingFollowRedirects":"global","_type":"request"},{"_id":"req_6a4793e104274112b63247971079e01e","parentId":"fld_1374896991c8448c9401786505583995","modified":1647708404190,"created":1647708296152,"url":"http://localhost:3333/buscar-um/1","name":"buscarUm","description":"","method":"GET","body":{},"parameters":[],"headers":[],"authentication":{},"metaSortKey":-1647708296152,"isPrivate":false,"settingStoreCookies":true,"settingSendCookies":true,"settingDisableRenderRequestBody":false,"settingEncodeUrl":true,"settingRebuildPath":true,"settingFollowRedirects":"global","_type":"request"},{"_id":"req_8cef2ce86a164e24b0a37d360a52361c","parentId":"fld_1374896991c8448c9401786505583995","modified":1647706688442,"created":1647706657471,"url":"http://localhost:3333/listar-acidez","name":"listarAcidez","description":"","method":"GET","body":{},"parameters":[],"headers":[],"authentication":{},"metaSortKey":-1647706657471,"isPrivate":false,"settingStoreCookies":true,"settingSendCookies":true,"settingDisableRenderRequestBody":false,"settingEncodeUrl":true,"settingRebuildPath":true,"settingFollowRedirects":"global","_type":"request"},{"_id":"req_b6dc18d7f79541caa631088f73fef77f","parentId":"fld_1374896991c8448c9401786505583995","modified":1647822722979,"created":1647706455911,"url":"http://localhost:3333/cadastrar-acidez","name":"cadastraAcidez","description":"","method":"POST","body":{"mimeType":"application/json","text":"{\n\t\"nome\":\"Média alta\",\n\t\"descricao\":\"Nenhuma descrição\"\n}"},"parameters":[],"headers":[{"name":"Content-Type","value":"application/json","id":"pair_77de24aa884d4a2db01eed14d528e001"}],"authentication":{},"metaSortKey":-1647706455911,"isPrivate":false,"settingStoreCookies":true,"settingSendCookies":true,"settingDisableRenderRequestBody":false,"settingEncodeUrl":true,"settingRebuildPath":true,"settingFollowRedirects":"global","_type":"request"},{"_id":"req_747328a7c083413d83dc22aa100de129","parentId":"fld_e9f47806fefc4170aee0e1b81edd7e56","modified":1647823585382,"created":1647821874912,"url":"http://localhost:3333/search-cafe?valorDaPesquisa=Caf","name":"buscarPorPalavra","description":"","method":"GET","body":{},"parameters":[],"headers":[],"authentication":{},"metaSortKey":-1647821874912,"isPrivate":false,"settingStoreCookies":true,"settingSendCookies":true,"settingDisableRenderRequestBody":false,"settingEncodeUrl":true,"settingRebuildPath":true,"settingFollowRedirects":"global","_type":"request"},{"_id":"fld_e9f47806fefc4170aee0e1b81edd7e56","parentId":"wrk_9d2642ba0e644f468825d682d3f05ecf","modified":1647100785045,"created":1647100785045,"name":"Cafe","description":"","environment":{},"environmentPropertyOrder":null,"metaSortKey":-1647100785045,"_type":"request_group"},{"_id":"req_27529aa8a05a4629bafd5d22a0d11f95","parentId":"fld_e9f47806fefc4170aee0e1b81edd7e56","modified":1647824634159,"created":1647350311599,"url":"http://localhost:3333/cafe-put/46","name":"AtualizarCafe","description":"","method":"PUT","body":{"mimeType":"application/json","text":"{\n\t\"nome\":\"Café Mantiqueira de Minas \",\n\t\"foto_cafe\":\"https://alavoura.com.br/wp-content/uploads/2020/06/tim-e1592429928966.jpeg\",\n\t\"foto_cafe_1\":\"https://alavoura.com.br/wp-content/uploads/2020/06/article.png\",\n\t\"foto_cafe_2\":\"https://alavoura.com.br/wp-content/uploads/2020/06/Cafe%CC%81-Ouro-da-Mantiqueira.jpg\",\n\t\"nota\":\"Uva vermelha\",\n\t\"peso_liquido\":\"250g\",\n\t\"preco\":\"50.50\",\n\t\"regiao_id\":2,\n\t\"corpo_id\":4,\n\t\"variedade_id\":4,\n\t\"torra_id\":3,\n\t\"acidez_id\":4,\n\t\"moagem_id\":4,\n\t\"descricao\":\"Nenhuma descrição\"\n \t\n}"},"parameters":[],"headers":[{"name":"Content-Type","value":"application/json","id":"pair_da8038dd74624e89b035688e2811f115"}],"authentication":{},"metaSortKey":-1647350311599,"isPrivate":false,"settingStoreCookies":true,"settingSendCookies":true,"settingDisableRenderRequestBody":false,"settingEncodeUrl":true,"settingRebuildPath":true,"settingFollowRedirects":"global","_type":"request"},{"_id":"req_ef21d21106f74a2392022b39cf20593d","parentId":"fld_e9f47806fefc4170aee0e1b81edd7e56","modified":1647824693029,"created":1647348137866,"url":"http://localhost:3333/cafe-delete/47","name":"DeletarCafe","description":"","method":"DELETE","body":{},"parameters":[],"headers":[],"authentication":{},"metaSortKey":-1647348137866,"isPrivate":false,"settingStoreCookies":true,"settingSendCookies":true,"settingDisableRenderRequestBody":false,"settingEncodeUrl":true,"settingRebuildPath":true,"settingFollowRedirects":"global","_type":"request"},{"_id":"req_9843f0c4c448402e833078c285058a47","parentId":"fld_e9f47806fefc4170aee0e1b81edd7e56","modified":1647823475210,"created":1647184858615,"url":"http://localhost:3333/cafes-por-regiao/2","name":"ListarCafePorRegiao","description":"","method":"GET","body":{},"parameters":[],"headers":[],"authentication":{},"metaSortKey":-1647184858615,"isPrivate":false,"settingStoreCookies":true,"settingSendCookies":true,"settingDisableRenderRequestBody":false,"settingEncodeUrl":true,"settingRebuildPath":true,"settingFollowRedirects":"global","_type":"request"},{"_id":"req_b38e9bd8b9774a97bc6a8fa41863b9d4","parentId":"fld_e9f47806fefc4170aee0e1b81edd7e56","modified":1647184307079,"created":1647184294822,"url":"http://localhost:3333/cafes","name":"ListarCafes","description":"","method":"GET","body":{},"parameters":[],"headers":[],"authentication":{},"metaSortKey":-1647184294822,"isPrivate":false,"settingStoreCookies":true,"settingSendCookies":true,"settingDisableRenderRequestBody":false,"settingEncodeUrl":true,"settingRebuildPath":true,"settingFollowRedirects":"global","_type":"request"},{"_id":"req_b77dca0a946b4e7d88a53b495011b75e","parentId":"fld_e9f47806fefc4170aee0e1b81edd7e56","modified":1647824661751,"created":1647100799536,"url":"http://localhost:3333/cadastra-cafe","name":"Cadastra","description":"","method":"POST","body":{"mimeType":"application/json","text":"{\n\t\"nome\":\"Café Mantiqueira de Minas\",\n\t\"foto_cafe\":\"https://alavoura.com.br/wp-content/uploads/2020/06/tim-e1592429928966.jpeg\",\n\t\"foto_cafe_1\":\"https://alavoura.com.br/wp-content/uploads/2020/06/article.png\",\n\t\"foto_cafe_2\":\"https://alavoura.com.br/wp-content/uploads/2020/06/Cafe%CC%81-Ouro-da-Mantiqueira.jpg\",\n\t\"nota\":\"Uva vermelha\",\n\t\"peso_liquido\":\"250g\",\n\t\"preco\":\"50.50\",\n\t\"regiao_id\":2,\n\t\"corpo_id\":4,\n\t\"variedade_id\":4,\n\t\"torra_id\":3,\n\t\"acidez_id\":4,\n\t\"moagem_id\":4,\n\t\"descricao\":\"Nenhuma descrição\"\n \t\n}"},"parameters":[],"headers":[{"name":"Content-Type","value":"application/json","id":"pair_1be9173c781e4435b613b781c7daa26d"}],"authentication":{},"metaSortKey":-1647100799536,"isPrivate":false,"settingStoreCookies":true,"settingSendCookies":true,"settingDisableRenderRequestBody":false,"settingEncodeUrl":true,"settingRebuildPath":true,"settingFollowRedirects":"global","_type":"request"},{"_id":"req_54a712f5e00d4c64bfac8f3a8b55104e","parentId":"fld_13ae9bdc14b741ceb0abedf32a3cfb14","modified":1647736827654,"created":1647736584921,"url":"http://localhost:3333/buscar-regiao/1","name":"buscarUmaRegiao","description":"","method":"GET","body":{},"parameters":[],"headers":[],"authentication":{},"metaSortKey":-1647736584921,"isPrivate":false,"settingStoreCookies":true,"settingSendCookies":true,"settingDisableRenderRequestBody":false,"settingEncodeUrl":true,"settingRebuildPath":true,"settingFollowRedirects":"global","_type":"request"},{"_id":"fld_13ae9bdc14b741ceb0abedf32a3cfb14","parentId":"wrk_9d2642ba0e644f468825d682d3f05ecf","modified":1646183014565,"created":1646183014565,"name":"Regiao","description":"","environment":{},"environmentPropertyOrder":null,"metaSortKey":-1646183014565,"_type":"request_group"},{"_id":"req_617fccc0e8ee45b99c40f3054afb86b3","parentId":"fld_13ae9bdc14b741ceb0abedf32a3cfb14","modified":1646579239504,"created":1646576914387,"url":"http://localhost:3333/search?valorDaPesquisa=Argfdfdf","name":"PesquisarRegiao","description":"","method":"GET","body":{},"parameters":[],"headers":[],"authentication":{},"metaSortKey":-1646576914387,"isPrivate":false,"settingStoreCookies":true,"settingSendCookies":true,"settingDisableRenderRequestBody":false,"settingEncodeUrl":true,"settingRebuildPath":true,"settingFollowRedirects":"global","_type":"request"},{"_id":"req_fbec7056f7cb45b29012a08485c2a385","parentId":"fld_13ae9bdc14b741ceb0abedf32a3cfb14","modified":1647822897603,"created":1646576662156,"url":"http://localhost:3333/atualiza/2","name":"AtualizarRegiao","description":"","method":"PUT","body":{"mimeType":"application/json","text":"\t{\n\t\t\n\t\t\"foto_bandeira\":\"https://rondonia.ro.gov.br/wp-content/uploads/2020/09/Bandeira-Nacionals%C3%ADmbolo-maior-da-P%C3%A1tria-Brasileira-Foto-Divulga%C3%A7%C3%A3o.jpg\",  \n   \"pais\":\"Brasil\", \n   \"descricao\":\"Nenhuma descrição\",\n   \"altitude\":\"1200\"\n\n\t\n\t}"},"parameters":[],"headers":[{"name":"Content-Type","value":"application/json","id":"pair_988e3167f55649e2bc37cbc94f2e1d0a"}],"authentication":{},"metaSortKey":-1646576662156,"isPrivate":false,"settingStoreCookies":true,"settingSendCookies":true,"settingDisableRenderRequestBody":false,"settingEncodeUrl":true,"settingRebuildPath":true,"settingFollowRedirects":"global","_type":"request"},{"_id":"req_784da130e0bc494f994a215db9fd9879","parentId":"fld_13ae9bdc14b741ceb0abedf32a3cfb14","modified":1646576813828,"created":1646576155371,"url":"http://localhost:3333/deleta/5","name":"DeletarRegiao","description":"","method":"DELETE","body":{"mimeType":"application/json","text":""},"parameters":[],"headers":[{"name":"Content-Type","value":"application/json","id":"pair_3817e6c92caa4080aa1bc1f10fd00439"}],"authentication":{},"metaSortKey":-1646576155371,"isPrivate":false,"settingStoreCookies":true,"settingSendCookies":true,"settingDisableRenderRequestBody":false,"settingEncodeUrl":true,"settingRebuildPath":true,"settingFollowRedirects":"global","_type":"request"},{"_id":"req_ce24cafd43e543ec9eabfb831deefdd1","parentId":"fld_13ae9bdc14b741ceb0abedf32a3cfb14","modified":1646576761265,"created":1646576102191,"url":"http://localhost:3333/regioes","name":"ListaRegiao","description":"","method":"GET","body":{},"parameters":[],"headers":[],"authentication":{},"metaSortKey":-1646183014665,"isPrivate":false,"settingStoreCookies":true,"settingSendCookies":true,"settingDisableRenderRequestBody":false,"settingEncodeUrl":true,"settingRebuildPath":true,"settingFollowRedirects":"global","_type":"request"},{"_id":"req_143504c14eff47b1afd7736fb9cd41bc","parentId":"fld_13ae9bdc14b741ceb0abedf32a3cfb14","modified":1647823171114,"created":1646183002551,"url":"http://localhost:3333/cadastrar-regiao","name":"CadastraRegiao","description":"","method":"POST","body":{"mimeType":"application/json","text":"{\n\t\"foto_bandeira\":\"https://rondonia.ro.gov.br/wp-content/uploads/2020/09/Bandeira-Nacionals%C3%ADmbolo-maior-da-P%C3%A1tria-Brasileira-Foto-Divulga%C3%A7%C3%A3o.jpg\",  \n   \"pais\":\"Brasil\", \n   \"descricao\":\"É um localizado na America do sul e é um dos maiores produtores de café do mundo\",\n   \"altitude\":1\n}"},"parameters":[],"headers":[{"name":"Content-Type","value":"application/json","id":"pair_c88733bb21a04ad58b65cf4593a80d5e"}],"authentication":{},"metaSortKey":-1646183014615,"isPrivate":false,"settingStoreCookies":true,"settingSendCookies":true,"settingDisableRenderRequestBody":false,"settingEncodeUrl":true,"settingRebuildPath":true,"settingFollowRedirects":"global","_type":"request"},{"_id":"env_97cbad85e8230d47e9d7ac7e0c5daad9a2fd7104","parentId":"wrk_9d2642ba0e644f468825d682d3f05ecf","modified":1647824718031,"created":1646182968076,"name":"Base Environment","data":{},"dataPropertyOrder":{},"color":null,"isPrivate":false,"metaSortKey":1646182968077,"_type":"environment"},{"_id":"jar_97cbad85e8230d47e9d7ac7e0c5daad9a2fd7104","parentId":"wrk_9d2642ba0e644f468825d682d3f05ecf","modified":1646182968081,"created":1646182968081,"name":"Default Jar","cookies":[],"_type":"cookie_jar"},{"_id":"spc_6c78a469411442cba5d71fb12c534c84","parentId":"wrk_9d2642ba0e644f468825d682d3f05ecf","modified":1646182968067,"created":1646182968067,"fileName":"api-cafe","contents":"","contentType":"yaml","_type":"api_spec"}]}